malta/__init__.py
malta/model.py
malta/transport.py
malta/utils.py
malta-0.3.1.dist-info/licenses/LICENSE
malta-0.3.1.dist-info/METADATA
malta-0.3.1.dist-info/WHEEL
malta-0.3.1.dist-info/top_level.txt
malta-0.3.1.dist-info/RECORD
