Metadata-Version: 2.4
Name: malta
Version: 0.3.1
Summary: A 2D model of atmospheric transport
Author: Luke Western
License: MIT
Requires-Python: >=3.9, <3.11
License-File: LICENSE
Requires-Dist: numpy==1.24.4
Requires-Dist: pandas==2.0.3
Requires-Dist: xarray==2023.10.1
Requires-Dist: numba==0.58.1
Requires-Dist: scipy>=1.11.4
Requires-Dist: matplotlib>=3.8.0
Requires-Dist: netCDF4>=1.7.2
Dynamic: author
Dynamic: description
Dynamic: description-content-type
Dynamic: license
Dynamic: license-file
Dynamic: requires-dist
Dynamic: requires-python
Dynamic: summary
